tapyfi/OHLCObject.py
tapyfi/__init__.py
tapyfi/__main__.py
tapyfi/Helpers/MAs.py
tapyfi/Helpers/__init__.py
tapyfi/Indicators/RSI.py
tapyfi/Indicators/__init__.py
tapyfi-1.1.8.dist-info/LICENSE.txt
tapyfi-1.1.8.dist-info/METADATA
tapyfi-1.1.8.dist-info/WHEEL
tapyfi-1.1.8.dist-info/entry_points.txt
tapyfi-1.1.8.dist-info/top_level.txt
tapyfi-1.1.8.dist-info/RECORD
